xpublish_edr/__init__.py
xpublish_edr/_version.py
xpublish_edr/format.py
xpublish_edr/logger.py
xpublish_edr/metadata.py
xpublish_edr/plugin.py
xpublish_edr/query.py
xpublish_edr/utils.py
xpublish_edr/formats/to_covjson.py
xpublish_edr/formats/to_csv.py
xpublish_edr/formats/to_geojson.py
xpublish_edr/formats/to_geotiff.py
xpublish_edr/formats/to_netcdf.py
xpublish_edr/formats/to_parquet.py
xpublish_edr/geometry/__init__.py
xpublish_edr/geometry/area.py
xpublish_edr/geometry/bbox.py
xpublish_edr/geometry/common.py
xpublish_edr/geometry/position.py
xpublish_edr-0.9.1.dist-info/licenses/LICENSE.txt
xpublish_edr-0.9.1.dist-info/METADATA
xpublish_edr-0.9.1.dist-info/WHEEL
xpublish_edr-0.9.1.dist-info/entry_points.txt
xpublish_edr-0.9.1.dist-info/top_level.txt
xpublish_edr-0.9.1.dist-info/RECORD
