Metadata-Version: 2.4
Name: xpublish_edr
Version: 0.9.1
License: Copyright 2017 AUTHOR NAME
Classifier: Development Status :: 5 - Production/Stable
Classifier: Intended Audience :: Science/Research
Classifier: Operating System :: OS Independent
Classifier: License :: OSI Approved :: BSD License
Classifier: Programming Language :: Python
Classifier: Programming Language :: Python :: 3
Classifier: Programming Language :: Python :: 3.11
Classifier: Programming Language :: Python :: 3.12
Classifier: Programming Language :: Python :: 3.13
Classifier: Topic :: Scientific/Engineering
Requires-Python: >=3.11
License-File: LICENSE.txt
Requires-Dist: geopandas
Requires-Dist: pyarrow
Requires-Dist: rioxarray
Requires-Dist: scipy
Requires-Dist: shapely
Requires-Dist: xarray
Requires-Dist: xpublish>=0.4.1
Dynamic: license-file
